{
  "name" : "Nouveau rapport 4",
  "modified" : "2019-05-04 10:34:01",
  "requires" : [ "scheme.ART", "graph.tcpos", "scheme.TRA_ART" ],
  "username" : "alebacq",
  "document_id" : 244891794,
  "type" : "REPORT",
  "report" : {"properties":{"css":{"header":{"text-transform":"uppercase"}},"active_step":"s1"},"steps":[{"alias":"s0","columns":[{"alias":"s0_c0","name":"UID article","expression":{"path":"tcpos.ART.ARTICLE_ID","type":"ID","resettable":false},"resettable":false}],"grouping":false,"name":"Articles","properties":{"scheme":"Articles"},"chart":false,"scheme":"ART"},{"alias":"s1","columns":[{"alias":"s1_c0","name":"Montant effectif ligne","expression":{"path":"tcpos.TRA_ART.AMOUNT","type":"DECIMAL","resettable":false},"properties":{"format":"0,0.00","format_unit":"CHF","format_pos":"prefix","format_dec_length":2,"format_mand_decimals":true,"format_type":"unit"},"resettable":false},{"alias":"s1_c1","name":"Article avec promotion","expression":{"path":"tcpos.TRA_ART.IS_PROMOTION","type":"BOOLEAN","resettable":false},"resettable":false},{"alias":"s1_c2","name":"Date","expression":{"path":"tcpos.TRA.BOOKKEEPING_DATE","type":"DATE","resettable":false},"resettable":false},{"alias":"s1_c3","name":"Heure","expression":{"path":"tcpos.TRA.TRANS_TIME","type":"TIME","resettable":false},"filter":{"items":[{"comparator":"IS_EQUAL","expression":{"type":"TIME","value":"18:00"},"display":"18:00"}],"and_or":"AND"},"properties":{"format":"HH:mm:ss"},"resettable":false},{"alias":"s1_c4","name":"Groupe A","expression":{"path":"tcpos.GRA.DESCRIPTION","type":"TEXT","resettable":false},"properties":{"width":250.0},"resettable":false}],"grouping":false,"name":"Tickets - lignes","properties":{"scheme":"Tickets - lignes"},"chart":false,"scheme":"TRA_ART"}] },
  "company" : "tekoe_tokudb",
  "translatable" : false,
  "folder_id" : -1833453596,
  "keep_version" : false
}