{
  "translations" : {
    "DE" : {
      "name" : "Kassencode",
      "category" : "Kassen",
      "comment" : "Code der Kasse"
    },
    "EN" : {
      "name" : "Cash desk Code",
      "category" : "Cash desks",
      "comment" : "Cash desk code"
    },
    "FR" : {
      "name" : "Code caisse",
      "category" : "Caisses",
      "comment" : "Code de la caisse"
    }
  },
  "name" : "Code caisse",
  "category" : "Caisses",
  "comment" : "Code de la caisse",
  "requires" : "graph.tcpos;auth.scheme.TRA_CAR | auth.scheme.TRA_TAB | auth.scheme.TRA | auth.scheme.DRA | auth.scheme.TRA_MEN | auth.scheme.TRA_PAY | auth.scheme.TIL | auth.scheme.TRA_POI | auth.scheme.TRA_ART_DIS | auth.scheme.WIT_TRA | auth.scheme.TRA_ART_PRO | auth.scheme.TRA_ART | _SYS_",
  "sql" : "{{TIL}}.`CODE`",
  "path" : "tcpos.TIL.CODE",
  "type" : "TEXT",
  "graph" : "tcpos",
  "refers_to_table" : true,
  "company" : "tekoe_tokudb"
}